netlify_py/__init__.py
netlify_py/netlify_py.py
netlify_py/apis/__init__.py
netlify_py/apis/api_base.py
netlify_py/apis/deploy.py
netlify_py/apis/exceptions.py
netlify_py/apis/sites.py
tests/__init__.py
tests/test_deploys.py
tests/test_sites.py
netlify_py-0.1.0.dist-info/LICENSE
netlify_py-0.1.0.dist-info/METADATA
netlify_py-0.1.0.dist-info/WHEEL
netlify_py-0.1.0.dist-info/top_level.txt
netlify_py-0.1.0.dist-info/RECORD
