Metadata-Version: 2.1
Name: netlify-py
Version: 0.1.0
Summary: A python wrapper for creating, managing and deploying sites to Netlify using the Netlify APIs.
Home-page: https://github.com/akshay-realiq/netlify_py
Author: akshay kumar c
Author-email: akshay@realiq.io
License: MIT License
Platform: UNKNOWN
Classifier: Development Status :: 3 - Alpha
Classifier: Intended Audience :: Developers
Classifier: Topic :: Software Development :: Libraries :: Python Modules
Classifier: Environment :: Web Environment
Classifier: License :: OSI Approved :: MIT License
Classifier: Operating System :: OS Independent
Classifier: Programming Language :: Python :: 3
Requires-Dist: requests
